features_from_dlc/__init__.py
features_from_dlc/features_from_dlc.py
features_from_dlc-2025.1.9.dist-info/METADATA
features_from_dlc-2025.1.9.dist-info/WHEEL
features_from_dlc-2025.1.9.dist-info/licenses/LICENCE
features_from_dlc-2025.1.9.dist-info/RECORD
