Metadata-Version: 2.4
Name: features-from-dlc
Version: 2025.1.9
Summary: Behavioral quantification from DeepLabCut tracking
Project-URL: Source Code, https://github.com/TeamNCMC/features-from-dlc
Author-email: Guillaume Le Goc <g.legoc@posteo.org>
License: MIT
License-File: LICENCE
Classifier: Programming Language :: Python :: 3.12
Requires-Python: >=3.12
Requires-Dist: h5py>=3.11
Requires-Dist: ipykernel
Requires-Dist: ipympl
Requires-Dist: ipython
Requires-Dist: ipywidgets
Requires-Dist: matplotlib>=3.9.0
Requires-Dist: natsort
Requires-Dist: notebook
Requires-Dist: numpy>=2.1
Requires-Dist: pandas>=2.2.3
Requires-Dist: pingouin>=0.5.5
Requires-Dist: scipy
Requires-Dist: seaborn>=0.13.2
Requires-Dist: shapely>=2.0.4
Requires-Dist: tables>=3.10.1
Requires-Dist: tqdm
